azuracast_sse_client/__init__.py
azuracast_sse_client/azuracast_sse_client.py
azuracast_sse_client-0.1.0.dist-info/LICENSE
azuracast_sse_client-0.1.0.dist-info/METADATA
azuracast_sse_client-0.1.0.dist-info/WHEEL
azuracast_sse_client-0.1.0.dist-info/top_level.txt
azuracast_sse_client-0.1.0.dist-info/RECORD
