Metadata-Version: 2.1
Name: azuracast-sse-client
Version: 0.1.0
Summary: Python SSE client for Azuracast
Home-page: https://github.com/joemcmahon/azuracast-sse-client
Author: Joe McMahon
Author-email: joe.mcmahon@example.com
Classifier: Programming Language :: Python :: 3
Classifier: License :: OSI Approved :: MIT License
Classifier: Operating System :: OS Independent
Requires-Python: >=3.10
License-File: LICENSE
Requires-Dist: aiohappyeyeballs==2.4.4
Requires-Dist: aiohttp==3.11.11
Requires-Dist: aiosignal==1.3.2
Requires-Dist: async-timeout==5.0.1
Requires-Dist: attrs==24.3.0
Requires-Dist: certifi==2024.12.14
Requires-Dist: charset-normalizer==3.4.1
Requires-Dist: discord.py==2.4.0
Requires-Dist: discord-webhook==1.3.1
Requires-Dist: frozenlist==1.5.0
Requires-Dist: idna==3.10
Requires-Dist: multidict==6.1.0
Requires-Dist: pip==24.3.1
Requires-Dist: propcache==0.2.1
Requires-Dist: python-dotenv==1.0.1
Requires-Dist: requests==2.32.3
Requires-Dist: setuptools==65.5.0
Requires-Dist: six==1.17.0
Requires-Dist: sseclient-py==1.8.0
Requires-Dist: typing_extensions==4.12.2
Requires-Dist: tzlocal==5.2
Requires-Dist: urllib3==2.3.0
Requires-Dist: yarl==1.18.3
